{"nodes": [{"id": "c_users_user_documents_websites_david_australia_meridian_3pl_meridian_3pl_src_lib_server_db_schema_ts", "label": "schema.ts", "file_type": "code", "source_file": "C:\\Users\\USER\\Documents\\WEBSITES\\David Australia\\MERIDIAN 3PL\\meridian-3pl\\src\\lib\\server\\db\\schema.ts", "source_location": "L1"}, {"id": "db_schema_jsonb", "label": "jsonb()", "file_type": "code", "source_file": "C:\\Users\\USER\\Documents\\WEBSITES\\David Australia\\MERIDIAN 3PL\\meridian-3pl\\src\\lib\\server\\db\\schema.ts", "source_location": "L20"}], "edges": [{"source": "c_users_user_documents_websites_david_australia_meridian_3pl_meridian_3pl_src_lib_server_db_schema_ts", "target": "drizzle_orm", "relation": "imports_from", "confidence": "EXTRACTED", "source_file": "C:\\Users\\USER\\Documents\\WEBSITES\\David Australia\\MERIDIAN 3PL\\meridian-3pl\\src\\lib\\server\\db\\schema.ts", "source_location": "L1", "weight": 1.0}, {"source": "c_users_user_documents_websites_david_australia_meridian_3pl_meridian_3pl_src_lib_server_db_schema_ts", "target": "mysql_core", "relation": "imports_from", "confidence": "EXTRACTED", "source_file": "C:\\Users\\USER\\Documents\\WEBSITES\\David Australia\\MERIDIAN 3PL\\meridian-3pl\\src\\lib\\server\\db\\schema.ts", "source_location": "L2", "weight": 1.0}, {"source": "c_users_user_documents_websites_david_australia_meridian_3pl_meridian_3pl_src_lib_server_db_schema_ts", "target": "db_schema_jsonb", "relation": "contains", "confidence": "EXTRACTED", "source_file": "C:\\Users\\USER\\Documents\\WEBSITES\\David Australia\\MERIDIAN 3PL\\meridian-3pl\\src\\lib\\server\\db\\schema.ts", "source_location": "L20", "weight": 1.0}], "raw_calls": [{"caller_nid": "db_schema_jsonb", "callee": "customType<{ data: TData; driverData: string }>({\n\t\tdataType() {\n\t\t\treturn 'json';\n\t\t},\n\t\ttoDriver(value: TData): string {\n\t\t\treturn JSON.stringify(value);\n\t\t},\n\t\tfromDriver(value: string | TData): TData {\n\t\t\treturn typeof value === 'string' ? (JSON.parse(value) as TData) : (value as TData);\n\t\t}\n\t})", "is_member_call": false, "source_file": "C:\\Users\\USER\\Documents\\WEBSITES\\David Australia\\MERIDIAN 3PL\\meridian-3pl\\src\\lib\\server\\db\\schema.ts", "source_location": "L21"}, {"caller_nid": "db_schema_jsonb", "callee": "customType", "is_member_call": false, "source_file": "C:\\Users\\USER\\Documents\\WEBSITES\\David Australia\\MERIDIAN 3PL\\meridian-3pl\\src\\lib\\server\\db\\schema.ts", "source_location": "L21"}]}